baselines/__init__.py
baselines/EntiGraph/__init__.py
baselines/EntiGraph/entigraph.py
baselines/Genie/__init__.py
baselines/Genie/genie.py
baselines/LongForm/__init__.py
baselines/LongForm/longform.py
baselines/SELF-QA/__init__.py
baselines/SELF-QA/self-qa.py
baselines/Wrap/__init__.py
baselines/Wrap/wrap.py
graphg-20250416.dist-info/licenses/LICENSE
graphgen/__init__.py
graphgen/evaluate.py
graphgen/generate.py
graphgen/graphgen.py
graphgen/judge.py
graphgen/version.py
graphgen/configs/graphgen_config.yaml
graphgen/models/__init__.py
graphgen/models/embed/__init__.py
graphgen/models/embed/embedding.py
graphgen/models/evaluate/__init__.py
graphgen/models/evaluate/base_evaluator.py
graphgen/models/evaluate/length_evaluator.py
graphgen/models/evaluate/mtld_evaluator.py
graphgen/models/evaluate/reward_evaluator.py
graphgen/models/evaluate/uni_evaluator.py
graphgen/models/llm/__init__.py
graphgen/models/llm/limitter.py
graphgen/models/llm/openai_model.py
graphgen/models/llm/tokenizer.py
graphgen/models/llm/topk_token_model.py
graphgen/models/search/__init__.py
graphgen/models/search/wiki_search.py
graphgen/models/storage/__init__.py
graphgen/models/storage/base_storage.py
graphgen/models/storage/json_storage.py
graphgen/models/storage/networkx_storage.py
graphgen/models/strategy/__init__.py
graphgen/models/strategy/base_strategy.py
graphgen/models/strategy/travserse_strategy.py
graphgen/models/text/__init__.py
graphgen/models/text/chunk.py
graphgen/models/text/text_pair.py
graphgen/operators/__init__.py
graphgen/operators/extract_kg.py
graphgen/operators/judge.py
graphgen/operators/merge_kg.py
graphgen/operators/quiz.py
graphgen/operators/resolute_coreference.py
graphgen/operators/search_wikipedia.py
graphgen/operators/split_graph.py
graphgen/operators/traverse_graph.py
graphgen/templates/__init__.py
graphgen/templates/answer_rephrasing.py
graphgen/templates/coreference_resolution.py
graphgen/templates/description_rephrasing.py
graphgen/templates/kg_extraction.py
graphgen/templates/kg_summarization.py
graphg-20250416.dist-info/METADATA
graphg-20250416.dist-info/WHEEL
graphg-20250416.dist-info/entry_points.txt
graphg-20250416.dist-info/top_level.txt
graphg-20250416.dist-info/RECORD
