Metadata-Version: 2.4
Name: graphg
Version: 20250416
Summary: GraphGen: Enhancing Supervised Fine-Tuning for LLMs with Knowledge-Driven Synthetic Data Generation
Home-page: https://github.com/open-sciencelab/GraphGen
Author: open-sciencelab
Author-email: open-sciencelab@pjlab.org.cn
Classifier: Programming Language :: Python :: 3.8
Classifier: Programming Language :: Python :: 3.9
Classifier: Programming Language :: Python :: 3.10
Classifier: Programming Language :: Python :: 3.11
Classifier: Programming Language :: Python :: 3.12
Classifier: Intended Audience :: Developers
Classifier: Intended Audience :: Education
Classifier: Intended Audience :: Science/Research
License-File: LICENSE
Requires-Dist: tqdm
Requires-Dist: openai
Requires-Dist: python-dotenv
Requires-Dist: numpy
Requires-Dist: networkx
Requires-Dist: graspologic
Requires-Dist: tiktoken
Requires-Dist: pyecharts
Requires-Dist: wikipedia
Requires-Dist: tenacity
Requires-Dist: nltk
Requires-Dist: jieba
Requires-Dist: plotly
Requires-Dist: pandas
Requires-Dist: gradio>=5.25.0
Requires-Dist: gradio-i18n==0.3.0
Requires-Dist: kaleido
Requires-Dist: pyyaml
Requires-Dist: langcodes
Dynamic: author
Dynamic: author-email
Dynamic: classifier
Dynamic: description
Dynamic: description-content-type
Dynamic: home-page
Dynamic: license-file
Dynamic: requires-dist
Dynamic: summary
